random_cat_gif/__init__.py
random_cat_gif-1.0.0.dist-info/METADATA
random_cat_gif-1.0.0.dist-info/WHEEL
random_cat_gif-1.0.0.dist-info/top_level.txt
random_cat_gif-1.0.0.dist-info/RECORD
