Metadata-Version: 2.1
Name: random-cat-gif
Version: 1.0.0
Summary: Who doesnt like a funny cat gif?
Home-page: https://github.com/applenana/random_cat_gif
Author: applenana
Author-email: 2806922724@qq.com
License: UNKNOWN
Platform: UNKNOWN
